AUTHORS
LICENSE
MANIFEST.in
README.rst
setup.py
allauth/__init__.py
allauth/app_settings.py
allauth/exceptions.py
allauth/models.py
allauth/tests.py
allauth/urls.py
allauth/utils.py
allauth/account/__init__.py
allauth/account/adapter.py
allauth/account/admin.py
allauth/account/app_settings.py
allauth/account/apps.py
allauth/account/auth_backends.py
allauth/account/context_processors.py
allauth/account/decorators.py
allauth/account/forms.py
allauth/account/managers.py
allauth/account/models.py
allauth/account/signals.py
allauth/account/tests.py
allauth/account/urls.py
allauth/account/utils.py
allauth/account/views.py
allauth/account/management/__init__.py
allauth/account/management/commands/__init__.py
allauth/account/management/commands/account_emailconfirmationmigration.py
allauth/account/management/commands/account_unsetmultipleprimaryemails.py
allauth/account/migrations/0001_initial.py
allauth/account/migrations/__init__.py
allauth/account/templatetags/__init__.py
allauth/account/templatetags/account.py
allauth/account/templatetags/account_tags.py
allauth/locale/cs/LC_MESSAGES/django.mo
allauth/locale/cs/LC_MESSAGES/django.po
allauth/locale/de/LC_MESSAGES/django.mo
allauth/locale/de/LC_MESSAGES/django.po
allauth/locale/el/LC_MESSAGES/django.mo
allauth/locale/el/LC_MESSAGES/django.po
allauth/locale/en/LC_MESSAGES/django.mo
allauth/locale/en/LC_MESSAGES/django.po
allauth/locale/es/LC_MESSAGES/django.mo
allauth/locale/es/LC_MESSAGES/django.po
allauth/locale/fa/LC_MESSAGES/django.mo
allauth/locale/fa/LC_MESSAGES/django.po
allauth/locale/fr/LC_MESSAGES/django.mo
allauth/locale/fr/LC_MESSAGES/django.po
allauth/locale/he/LC_MESSAGES/django.mo
allauth/locale/he/LC_MESSAGES/django.po
allauth/locale/hr/LC_MESSAGES/django.mo
allauth/locale/hr/LC_MESSAGES/django.po
allauth/locale/it/LC_MESSAGES/django.mo
allauth/locale/it/LC_MESSAGES/django.po
allauth/locale/ja/LC_MESSAGES/django.mo
allauth/locale/ja/LC_MESSAGES/django.po
allauth/locale/nl/LC_MESSAGES/django.mo
django_allauth_james.egg-info/PKG-INFO
django_allauth_james.egg-info/SOURCES.txt
django_allauth_james.egg-info/dependency_links.txt
django_allauth_james.egg-info/requires.txt
django_allauth_james.egg-info/top_level.txt