Metadata-Version: 1.1
Name: django-allauth-james
Version: 0.20.0
Summary: Temp fork: Integrated set of Django applications addressing authentication, registration, account management as well as 3rd party (social) account authentication.
Home-page: http://github.com/variable/django-allauth
Author: Raymond Penners
Author-email: raymond.penners@intenct.nl
License: UNKNOWN
Keywords: django auth account social openid twitter facebook oauth registration
Platform: UNKNOWN
Classifier: Development Status :: 4 - Beta
Classifier: Intended Audience :: Developers
Classifier: Topic :: Software Development :: Libraries :: Python Modules
Classifier: Environment :: Web Environment
Classifier: Topic :: Internet
Classifier: License :: OSI Approved :: MIT License
Classifier: Operating System :: OS Independent
Classifier: Programming Language :: Python
Classifier: Programming Language :: Python :: 2.6
Classifier: Programming Language :: Python :: 2.7
Classifier: Programming Language :: Python :: 3.3
Classifier: Programming Language :: Python :: 3.4
Classifier: Framework :: Django
